ml_adapter/sklearn/__init__.py
ml_adapter/sklearn/py.typed
waylay_ml_adapter_sklearn-0.1.1.dist-info/licenses/LICENCE.txt
waylay_ml_adapter_sklearn-0.1.1.dist-info/METADATA
waylay_ml_adapter_sklearn-0.1.1.dist-info/WHEEL
waylay_ml_adapter_sklearn-0.1.1.dist-info/top_level.txt
waylay_ml_adapter_sklearn-0.1.1.dist-info/RECORD
