Metadata-Version: 2.4
Name: waylay-ml-adapter-sklearn
Version: 0.1.1
Summary: ML_adapter for sklearn.
Author-email: Waylay <info@waylay.io>
Requires-Python: >=3.11
License-File: LICENCE.txt
Requires-Dist: waylay-ml-adapter-numpy
Provides-Extra: dev
Requires-Dist: waylay-ml-adapter-devtools; extra == "dev"
Requires-Dist: waylay-sdk-core; extra == "dev"
Requires-Dist: scikit-learn==1.5.*; extra == "dev"
Dynamic: license-file
